json5conf.py
json5conf-0.1.0.dist-info/METADATA
json5conf-0.1.0.dist-info/WHEEL
json5conf-0.1.0.dist-info/top_level.txt
json5conf-0.1.0.dist-info/RECORD
